{
  "run": {
    "command": "nx build @byeonghyeon/themes",
    "startTime": "2024-07-30T10:42:36.062Z",
    "endTime": "2024-07-30T10:42:41.196Z",
    "inner": false
  },
  "tasks": [
    {
      "taskId": "@byeonghyeon/esbuild-config:build",
      "target": "build",
      "projectName": "@byeonghyeon/esbuild-config",
      "hash": "5187349505263551225",
      "startTime": "2024-07-30T10:42:36.066Z",
      "endTime": "2024-07-30T10:42:37.184Z",
      "params": "",
      "cacheStatus": "cache-miss",
      "status": 0
    },
    {
      "taskId": "@byeonghyeon/themes:build",
      "target": "build",
      "projectName": "@byeonghyeon/themes",
      "hash": "11909150431792349755",
      "startTime": "2024-07-30T10:42:37.185Z",
      "endTime": "2024-07-30T10:42:41.195Z",
      "params": "",
      "cacheStatus": "cache-miss",
      "status": 0
    }
  ]
}